ejkernel/__init__.py
ejkernel/benchmarks.py
ejkernel/callib/__init__.py
ejkernel/callib/_ejit.py
ejkernel/callib/_pallas_call.py
ejkernel/callib/_triton_call.py
ejkernel/callib/_utils.py
ejkernel/kernels/__init__.py
ejkernel/kernels/_cuda/__init__.py
ejkernel/kernels/_pallas/__init__.py
ejkernel/kernels/_pallas/gpu/__init__.py
ejkernel/kernels/_pallas/gpu/ragged_decode_attention/__init__.py
ejkernel/kernels/_pallas/gpu/ragged_decode_attention/_interface.py
ejkernel/kernels/_pallas/gpu/ragged_decode_attention/_pallas_impl_fwd.py
ejkernel/kernels/_pallas/gpu/scaled_dot_product_attention/__init__.py
ejkernel/kernels/_pallas/gpu/scaled_dot_product_attention/_interface.py
ejkernel/kernels/_pallas/tpu/__init__.py
ejkernel/kernels/_pallas/tpu/blocksparse_attention/__init__.py
ejkernel/kernels/_pallas/tpu/blocksparse_attention/_info.py
ejkernel/kernels/_pallas/tpu/blocksparse_attention/_kernel.py
ejkernel/kernels/_pallas/tpu/blocksparse_attention/_masks.py
ejkernel/kernels/_pallas/tpu/flash_attention/__init__.py
ejkernel/kernels/_pallas/tpu/flash_attention/_interface.py
ejkernel/kernels/_pallas/tpu/flash_attention/_pallas_impl_bwd.py
ejkernel/kernels/_pallas/tpu/flash_attention/_pallas_impl_fwd.py
ejkernel/kernels/_pallas/tpu/flash_attention/_utils.py
ejkernel/kernels/_pallas/tpu/grouped_matmul/__init__.py
ejkernel/kernels/_pallas/tpu/grouped_matmul/_interface.py
ejkernel/kernels/_pallas/tpu/grouped_matmul/_pallas_impl.py
ejkernel/kernels/_pallas/tpu/grouped_matmul/_utils.py
ejkernel/kernels/_pallas/tpu/grouped_matmulv2/__init__.py
ejkernel/kernels/_pallas/tpu/grouped_matmulv2/_interface.py
ejkernel/kernels/_pallas/tpu/grouped_matmulv2/_pallas_impl.py
ejkernel/kernels/_pallas/tpu/page_attention/__init__.py
ejkernel/kernels/_pallas/tpu/page_attention/_interface.py
ejkernel/kernels/_pallas/tpu/page_attention/_pallas_impl_fwd.py
ejkernel/kernels/_pallas/tpu/prefill_page_attention/__init__.py
ejkernel/kernels/_pallas/tpu/prefill_page_attention/_interface.py
ejkernel-0.0.50.dist-info/WHEEL
ejkernel-0.0.50.dist-info/METADATA
ejkernel-0.0.50.dist-info/RECORD
