Metadata-Version: 2.3
Name: ejkernel
Version: 0.0.50
Summary: Accelerate, Optimize performance with streamlined training and serving options with JAX.
Keywords: Deep Learning,Machine Learning,JAX,CUDA,XLA,Triton,Pallas
Author: Erfan Zare Chavoshi
Author-email: Erfan Zare Chavoshi <Erfanzare810@gmail.com>
License: Apache-2.0
Classifier: Development Status :: 3 - Alpha
Classifier: Intended Audience :: Developers
Classifier: Topic :: Scientific/Engineering :: Artificial Intelligence
Classifier: License :: OSI Approved :: Apache Software License
Classifier: Programming Language :: Python :: 3.11
Classifier: Programming Language :: Python :: 3.12
Classifier: Programming Language :: Python :: 3.13
Requires-Dist: beartype>=0.22.2
Requires-Dist: chex>=0.1.91
Requires-Dist: einops>=0.8.1
Requires-Dist: jax~=0.8.2
Requires-Dist: jaxlib~=0.8.2
Requires-Dist: jaxtyping>=0.3.2
Requires-Dist: pydantic>=2.11.10
Requires-Dist: eformer ; extra == 'dev'
Requires-Dist: jax[cuda12]>=0.8.2 ; extra == 'gpu'
Requires-Dist: triton==3.4.0 ; extra == 'gpu'
Requires-Dist: xprof>=2.20.6 ; extra == 'profile'
Requires-Dist: tb-nightly>=2.21.0a20250820 ; extra == 'profile'
Requires-Dist: xprof-nightly>=2.21.6a20250820 ; extra == 'profile'
Requires-Dist: jax[tpu]>=0.8.2 ; extra == 'tpu'
Requires-Dist: triton==3.4.0 ; extra == 'triton'
Requires-Python: >=3.11, <3.14
Project-URL: Documentation, https://ejkernel.readthedocs.io/en/latest/
Project-URL: Homepage, https://github.com/erfanzar/ejkernel
Project-URL: Repository, https://github.com/erfanzar/ejkernel
Provides-Extra: dev
Provides-Extra: gpu
Provides-Extra: profile
Provides-Extra: tpu
Provides-Extra: triton
